wizmap/__init__.py
wizmap/wizmap.js
wizmap/wizmap.py
wizmap/__pycache__/__init__.cpython-312.pyc
wizmap/__pycache__/wizmap.cpython-312.pyc
wizmap-0.1.4.dist-info/METADATA
wizmap-0.1.4.dist-info/WHEEL
wizmap-0.1.4.dist-info/top_level.txt
wizmap-0.1.4.dist-info/RECORD
