Metadata-Version: 2.4
Name: wizmap
Version: 0.1.4
Summary: A Python package to run WizMap in your computational notebooks.
Home-page: https://github.com/poloclub/wizmap
Author: Jay Wang
Author-email: jayw@zijie.wang
License: MIT license
Keywords: Jupyter,JupyterLab,JupyterLab3,Machine Learning,Visualization,Interactive Visualization,Embeddings
Platform: Linux
Platform: Mac OS X
Platform: Windows
Classifier: License :: OSI Approved :: MIT License
Classifier: Programming Language :: Python
Classifier: Programming Language :: Python :: 3
Classifier: Programming Language :: Python :: 3.6
Classifier: Programming Language :: Python :: 3.7
Classifier: Programming Language :: Python :: 3.8
Classifier: Programming Language :: Python :: 3.9
Classifier: Framework :: Jupyter
Classifier: Framework :: Jupyter :: JupyterLab
Classifier: Framework :: Jupyter :: JupyterLab :: 3
Requires-Python: >=3.6
Requires-Dist: numpy
Requires-Dist: ipython
Requires-Dist: tqdm
Requires-Dist: quadtreed3
Requires-Dist: ndjson
Requires-Dist: scikit-learn
Dynamic: author
Dynamic: author-email
Dynamic: classifier
Dynamic: description
Dynamic: description-content-type
Dynamic: home-page
Dynamic: keywords
Dynamic: license
Dynamic: platform
Dynamic: requires-dist
Dynamic: requires-python
Dynamic: summary
